cloudmesh.comet-1.4.9-py3.6-nspkg.pth
cloudmesh/comet/__init__.py
cloudmesh/comet/authenticate.py
cloudmesh/comet/cluster.py
cloudmesh/comet/comet.py
cloudmesh/comet/command/__init__.py
cloudmesh/comet/command/comet.py
cloudmesh.comet-1.4.9.dist-info/DESCRIPTION.rst
cloudmesh.comet-1.4.9.dist-info/METADATA
cloudmesh.comet-1.4.9.dist-info/RECORD
cloudmesh.comet-1.4.9.dist-info/WHEEL
cloudmesh.comet-1.4.9.dist-info/metadata.json
cloudmesh.comet-1.4.9.dist-info/namespace_packages.txt
cloudmesh.comet-1.4.9.dist-info/top_level.txt
