Metadata-Version: 2.0
Name: cloudmesh.comet
Version: 1.4.9
Summary: A Command Line Client and Shell to Interact with Comet VC
Home-page: https://github.com/cloudmesh/cloudmesh.comet
Author: Gregor von Laszewski
Author-email: laszewski@gmail.com
License: Apache 2.0
Platform: UNKNOWN
Classifier: Development Status :: 5 - Production/Stable
Classifier: Environment :: Web Environment
Classifier: Intended Audience :: Developers
Classifier: License :: OSI Approved :: BSD License
Classifier: Operating System :: OS Independent
Classifier: Programming Language :: Python
Classifier: Programming Language :: Python :: 2
Classifier: Programming Language :: Python :: 3
Requires-Dist: cloudmesh.cmd5
Requires-Dist: httpsig
Requires-Dist: pytz
Requires-Dist: requests
Requires-Dist: requests-toolbelt
